accutuning_helpers/__init__.py
accutuning_helpers/ensemble_proxy.py
accutuning_helpers/feature_engineering/__init__.py
accutuning_helpers/feature_engineering/category_converter.py
accutuning_helpers/feature_engineering/chemical.py
accutuning_helpers/feature_engineering/datetime64_converter.py
accutuning_helpers/feature_engineering/lag_column_adder.py
accutuning_helpers/feature_engineering/onehotencoder.py
accutuning_helpers/feature_engineering/onehotencoder_support.py
accutuning_helpers/feature_engineering/timeseries.py
accutuning_helpers/preprocessing/__init__.py
accutuning_helpers/preprocessing/columnlabeler.py
accutuning_helpers/preprocessing/columnselector.py
accutuning_helpers/preprocessing/dtypeconvert.py
accutuning_helpers/preprocessing/integerencode.py
accutuning_helpers/preprocessing/nullimputer.py
accutuning_helpers/preprocessing/ordinalencoder_tmp.py
accutuning_helpers/preprocessing/outlier.py
accutuning_helpers/preprocessing/powertransformer.py
accutuning_helpers/preprocessing/sampler.py
accutuning_helpers/supports/__init__.py
accutuning_helpers/supports/pipeline.py
accutuning_helpers-1.1.0.dist-info/METADATA
accutuning_helpers-1.1.0.dist-info/WHEEL
accutuning_helpers-1.1.0.dist-info/top_level.txt
accutuning_helpers-1.1.0.dist-info/RECORD
